sparsecomputation/__init__.py
sparsecomputation/dimreducer.py
sparsecomputation/sparsecomputation.py
sparsecomputation-2019.6.3.dist-info/LICENSE.md
sparsecomputation-2019.6.3.dist-info/METADATA
sparsecomputation-2019.6.3.dist-info/WHEEL
sparsecomputation-2019.6.3.dist-info/top_level.txt
sparsecomputation-2019.6.3.dist-info/RECORD
