Metadata-Version: 2.1
Name: sparsecomputation
Version: 2019.6.3
Summary: Sparse Computation algorithm for sparsifying similarity matrices.
Home-page: https://github.com/hochbaumGroup/sparsecomputation
Author: Titouan Jehl, Quico Spaen, Philipp Baumann
Author-email: qspaen@berkeley.edu
License: Non-commercial license. Not an open-source license.
Keywords: pairwise similarity,classification,sparsification,clustering
Platform: UNKNOWN
Classifier: Development Status :: 3 - Alpha
Classifier: Programming Language :: Python :: 3.5
Requires-Dist: numpy
Requires-Dist: scipy
Requires-Dist: sklearn
Requires-Dist: six
